wrapperspotify.py
WrapperSpotify-1.0.6.dist-info/LICENSE
WrapperSpotify-1.0.6.dist-info/METADATA
WrapperSpotify-1.0.6.dist-info/WHEEL
WrapperSpotify-1.0.6.dist-info/top_level.txt
WrapperSpotify-1.0.6.dist-info/RECORD
