Metadata-Version: 2.1
Name: WrapperSpotify
Version: 1.0.6
Summary: A lightweight python client for the spotify
Home-page: https://github.com/Gwali-1/spotifyclient.git
Author: Matthew Gwalisam
Author-email: gwalisam37@gmail.com
License: MIT
Classifier: Programming Language :: Python :: 3
Classifier: License :: OSI Approved :: MIT License
Classifier: Operating System :: OS Independent
License-File: LICENSE
Requires-Dist: requests
